msl/examples/loadlib/Trig.class
msl/examples/loadlib/__init__.py
msl/examples/loadlib/cpp32.py
msl/examples/loadlib/cpp64.py
msl/examples/loadlib/cpp_lib32.dll
msl/examples/loadlib/cpp_lib64.dll
msl/examples/loadlib/dotnet32.py
msl/examples/loadlib/dotnet64.py
msl/examples/loadlib/dotnet_lib32.dll
msl/examples/loadlib/dotnet_lib64.dll
msl/examples/loadlib/echo32.py
msl/examples/loadlib/echo64.py
msl/examples/loadlib/fortran32.py
msl/examples/loadlib/fortran64.py
msl/examples/loadlib/fortran_lib32.dll
msl/examples/loadlib/fortran_lib64.dll
msl/examples/loadlib/java_lib.jar
msl/examples/loadlib/kernel32.py
msl/examples/loadlib/kernel64.py
msl/examples/loadlib/labview32.py
msl/examples/loadlib/labview64.py
msl/examples/loadlib/labview_lib32.dll
msl/examples/loadlib/labview_lib64.dll
msl/examples/loadlib/py.typed
msl/loadlib/__about__.py
msl/loadlib/__init__.py
msl/loadlib/_constants.py
msl/loadlib/_types.py
msl/loadlib/_version.py
msl/loadlib/activex.py
msl/loadlib/client64.py
msl/loadlib/exceptions.py
msl/loadlib/freeze_server32.py
msl/loadlib/load_library.py
msl/loadlib/py.typed
msl/loadlib/py4j-wrapper.jar
msl/loadlib/server32-windows.exe
msl/loadlib/server32-windows.exe.config
msl/loadlib/server32.py
msl/loadlib/start_server32.py
msl/loadlib/utils.py
msl_loadlib-1.0.0.dist-info/METADATA
msl_loadlib-1.0.0.dist-info/WHEEL
msl_loadlib-1.0.0.dist-info/entry_points.txt
msl_loadlib-1.0.0.dist-info/licenses/LICENSE.txt
msl_loadlib-1.0.0.dist-info/RECORD
