Metadata-Version: 2.4
Name: msl-loadlib
Version: 1.0.0
Summary: Load a library (and access a 32-bit library from 64-bit Python)
Project-URL: Changes, https://mslnz.github.io/msl-loadlib/latest/release-notes/
Project-URL: Documentation, https://mslnz.github.io/msl-loadlib/latest/
Project-URL: Homepage, https://mslnz.github.io/msl-loadlib/latest/
Project-URL: Source, https://github.com/MSLNZ/msl-loadlib
Project-URL: Tracker, https://github.com/MSLNZ/msl-loadlib/issues
Author-email: Measurement Standards Laboratory of New Zealand <info@measurement.govt.nz>
Maintainer-email: Joseph Borbely <joseph.borbely@measurement.govt.nz>
License: MIT License
License-File: LICENSE.txt
Classifier: Development Status :: 5 - Production/Stable
Classifier: Intended Audience :: Developers
Classifier: Intended Audience :: Science/Research
Classifier: License :: OSI Approved :: MIT License
Classifier: Operating System :: OS Independent
Classifier: Programming Language :: Python
Classifier: Programming Language :: Python :: 3
Classifier: Programming Language :: Python :: 3.8
Classifier: Programming Language :: Python :: 3.9
Classifier: Programming Language :: Python :: 3.10
Classifier: Programming Language :: Python :: 3.11
Classifier: Programming Language :: Python :: 3.12
Classifier: Programming Language :: Python :: 3.13
Classifier: Topic :: Scientific/Engineering
Classifier: Topic :: Software Development
Requires-Python: >=3.8
Provides-Extra: all
Requires-Dist: comtypes; (sys_platform == 'win32') and extra == 'all'
Requires-Dist: py4j; extra == 'all'
Requires-Dist: pythonnet; extra == 'all'
Provides-Extra: clr
Requires-Dist: pythonnet; extra == 'clr'
Provides-Extra: com
Requires-Dist: comtypes; extra == 'com'
Provides-Extra: java
Requires-Dist: py4j; extra == 'java'
